CHANGELOG.txt
LICENCE.txt
MANIFEST.in
README.txt
setup.py
foolscript/__init__.py
foolscript/shell.py
foolscript/user_pref.py
foolscript.egg-info/PKG-INFO
foolscript.egg-info/SOURCES.txt
foolscript.egg-info/dependency_links.txt
foolscript.egg-info/top_level.txt