Metadata-Version: 2.1
Name: foolscript
Version: 2.0.0
Summary: foolscript
Home-page: UNKNOWN
Author: Krishnavyshak
Author-email: krishnavyshak.dev@gmail.com
License: MIT
Keywords: calculator
Platform: UNKNOWN
Classifier: Development Status :: 5 - Production/Stable
Classifier: Intended Audience :: Education
Classifier: Operating System :: Microsoft :: Windows :: Windows 10
Classifier: License :: OSI Approved :: MIT License
Classifier: Programming Language :: Python :: 3
License-File: LICENCE.txt
